README.md
setup.cfg
setup.py
primoj/__init__.py
primoj/funcoes.py
primoj.egg-info/PKG-INFO
primoj.egg-info/SOURCES.txt
primoj.egg-info/dependency_links.txt
primoj.egg-info/top_level.txt