Metadata-Version: 1.0
Name: primoj
Version: 1.0.0
Summary: Descubra números primos
Home-page: https://github.com/avellar1975/primoj
Author: Evandro Avellar
Author-email: evandro.avellar@gmail.com
License: GNU Affero General Public License v3 or later (AGPLv3+)
Platform: UNKNOWN
